mcp_server_wechat/WechatClient.py
mcp_server_wechat/WechatServer.py
mcp_server_wechat/__init__.py
mcp_server_wechat/__main__.py
mcp_server_wechat-0.8.dist-info/licenses/LICENSE
mcp_server_wechat_Streamable_HTTP/WechatClient.py
mcp_server_wechat_Streamable_HTTP/__init__.py
mcp_server_wechat_Streamable_HTTP/__main__.py
mcp_server_wechat_Streamable_HTTP/server.py
mcp_server_wechat_sse/WechatClient.py
mcp_server_wechat_sse/WechatServer.py
mcp_server_wechat_sse/__init__.py
mcp_server_wechat_sse/__main__.py
mcp_server_wechat-0.8.dist-info/METADATA
mcp_server_wechat-0.8.dist-info/WHEEL
mcp_server_wechat-0.8.dist-info/top_level.txt
mcp_server_wechat-0.8.dist-info/RECORD
