Metadata-Version: 2.4
Name: mcp_server_wechat
Version: 0.8
Summary: 基于MCP技术的微信聊天记录获取和消息发送功能的服务器
Home-page: https://github.com/panxingfeng/mcp_server_wechat
Download-URL: https://github.com/panxingfeng/mcp_server_wechat/archive/refs/tags/0.7.tar.gz
Author: panxingfeng
Author-email: panxingfeng <1115005803@qq.com>
License: MIT
Project-URL: Homepage, https://github.com/panxingfeng/mcp_server_wechat
Project-URL: Download, https://github.com/panxingfeng/mcp_server_wechat/archive/refs/tags/0.8.tar.gz
Classifier: Development Status :: 3 - Alpha
Classifier: Intended Audience :: Developers
Classifier: Topic :: Communications :: Chat
Classifier: Topic :: Software Development :: Libraries :: Python Modules
Classifier: Topic :: Utilities
Classifier: Operating System :: Microsoft :: Windows
Classifier: Programming Language :: Python :: 3.11
Classifier: Natural Language :: Chinese (Simplified)
Requires-Python: >=3.11
License-File: LICENSE
Requires-Dist: pywechat127>=1.8.8
Requires-Dist: mcp==1.9.1
Requires-Dist: pywinauto==0.6.9
Requires-Dist: PyAutoGUI==0.9.54
Requires-Dist: starlette>=0.28.0
Requires-Dist: uvicorn>=0.24.0
Requires-Dist: sse-starlette>=1.6.5
Dynamic: author
Dynamic: download-url
Dynamic: home-page
Dynamic: license-file
